Metadata-Version: 1.1
Name: digTableExtractor
Version: 0.2.0
Summary: digTableExtractor
Home-page: https://github.com/usc-isi-i2/dig-table-extractor
Author: Vinay Rao Dandin
Author-email: vrdandin@isi.edu
License: UNKNOWN
Download-URL: https://github.com/usc-isi-i2/dig-table-extractor
Platform: UNKNOWN
